{
  "id": 84,
  "iv": "population",
  "dv": "fundraising_efficiency_w",
  "n": 117510,
  "beta": -5.770479603049092e-05,
  "pvalue": 0.0013252238665099815,
  "rsquared": 0.17557716911304544,
  "agent_analysis": {
    "hypothesis_direction": "negative",
    "hypothesis_rationale": "More populous ZIP codes have more charities, increasing competition and slightly reducing winsorized fundraising efficiency.",
    "prior_art_notes": "Rose-Ackerman (1982) outlines donor competition in populous/urban areas.",
    "strength": "weak",
    "interpretation": "A statistically significant but practically weak negative correlation was found. Nonprofits in high population ZIP codes face a very slight drop in winsorized fundraising efficiency."
  }
}